MANIFEST.in
README.rst
README.txt
setup.py
src/zc/__init__.py
src/zc.zkzeo.egg-info/PKG-INFO
src/zc.zkzeo.egg-info/SOURCES.txt
src/zc.zkzeo.egg-info/dependency_links.txt
src/zc.zkzeo.egg-info/entry_points.txt
src/zc.zkzeo.egg-info/namespace_packages.txt
src/zc.zkzeo.egg-info/not-zip-safe
src/zc.zkzeo.egg-info/requires.txt
src/zc.zkzeo.egg-info/top_level.txt
src/zc/zkzeo/README.rst
src/zc/zkzeo/__init__.py
src/zc/zkzeo/_client.py
src/zc/zkzeo/component.xml
src/zc/zkzeo/nagios.py
src/zc/zkzeo/runzeo.py
src/zc/zkzeo/schema.xml
src/zc/zkzeo/server-component.xml
src/zc/zkzeo/tests.py
src/zc/zkzeo/wait-for-zookeeper.test