Metadata-Version: 1.0
Name: zc.zkzeo
Version: 1.0.1
Summary: ZEO ZooKeeper
Home-page: UNKNOWN
Author: Jim Fulton
Author-email: jim@zope.com
License: ZPL 2.1
Platform: UNKNOWN
